streamlit_toggle_diy/__init__.py
streamlit_toggle_diy/frontend/build/asset-manifest.json
streamlit_toggle_diy/frontend/build/bootstrap.min.css
streamlit_toggle_diy/frontend/build/index.html
streamlit_toggle_diy/frontend/build/precache-manifest.208239bd31634c912148876425127f2c.js
streamlit_toggle_diy/frontend/build/precache-manifest.669f85f994ea2c0d193915faa9d91f97.js
streamlit_toggle_diy/frontend/build/service-worker.js
streamlit_toggle_diy/frontend/build/static/js/2.82cd69ef.chunk.js
streamlit_toggle_diy/frontend/build/static/js/2.82cd69ef.chunk.js.LICENSE.txt
streamlit_toggle_diy/frontend/build/static/js/2.82cd69ef.chunk.js.map
streamlit_toggle_diy/frontend/build/static/js/main.72a874a0.chunk.js
streamlit_toggle_diy/frontend/build/static/js/main.72a874a0.chunk.js.map
streamlit_toggle_diy/frontend/build/static/js/main.93eb9d37.chunk.js
streamlit_toggle_diy/frontend/build/static/js/main.93eb9d37.chunk.js.map
streamlit_toggle_diy/frontend/build/static/js/runtime-main.d76c522e.js
streamlit_toggle_diy/frontend/build/static/js/runtime-main.d76c522e.js.map
streamlit_toggle_diy/frontend/public/bootstrap.min.css
streamlit_toggle_diy/frontend/public/index.html
streamlit_toggle_diy/frontend/src/index.tsx
streamlit_toggle_diy/frontend/src/react-app-env.d.ts
streamlit_toggle_diy/frontend/src/streamlit_toggle.tsx
streamlit_toggle_diy/frontend/src/style.css
streamlit_toggle_switch_diy-1.1.2.dist-info/LICENSE
streamlit_toggle_switch_diy-1.1.2.dist-info/METADATA
streamlit_toggle_switch_diy-1.1.2.dist-info/WHEEL
streamlit_toggle_switch_diy-1.1.2.dist-info/top_level.txt
streamlit_toggle_switch_diy-1.1.2.dist-info/RECORD
